materialite/__init__.py
materialite/basis_operations.py
materialite/get_ipf_colors.py
materialite/importers.py
materialite/json_operations.py
materialite/material.py
materialite/slip_system.py
materialite/tensor.py
materialite/models/__init__.py
materialite/models/convolution_gpu_model.py
materialite/models/convolution_microstructure_model.py
materialite/models/convolution_model.py
materialite/models/decoupled_crystal_elasticity.py
materialite/models/grain_coarsening_model.py
materialite/models/model.py
materialite/models/taylor_model.py
materialite/models/small_strain_fft/__init__.py
materialite/models/small_strain_fft/elastic.py
materialite/models/small_strain_fft/elastic_viscoplastic.py
materialite/models/small_strain_fft/hardening_laws.py
materialite/models/small_strain_fft/isotropic_elastic_plastic.py
materialite/models/small_strain_fft/load_schedule.py
materialite/models/small_strain_fft/multiphase.py
materialite/models/small_strain_fft/small_strain_fft.py
materialite/util/__init__.py
materialite/util/util.py
materialite-0.1.3.dist-info/licenses/LICENSE
materialite-0.1.3.dist-info/METADATA
materialite-0.1.3.dist-info/WHEEL
materialite-0.1.3.dist-info/top_level.txt
materialite-0.1.3.dist-info/RECORD
