Metadata-Version: 2.4
Name: materialite
Version: 0.1.3
Summary: Streamlined microstructure modeling - A unified Python framework for materials science and mechanics research
Author: NASA Langley Research Center
License: 
Project-URL: Homepage, https://nasa.github.io/materialite
Project-URL: Repository, https://github.com/nasa/materialite
Project-URL: Issues, https://github.com/nasa/materialite/issues
Classifier: License :: OSI Approved :: Apache Software License
Classifier: Programming Language :: Python :: 3
Requires-Python: >=3.10
License-File: LICENSE
Requires-Dist: numpy
Requires-Dist: pandas
Requires-Dist: scipy
Requires-Dist: matplotlib
Requires-Dist: h5py
Requires-Dist: pyvista>=0.45
Requires-Dist: trame
Requires-Dist: trame-vtk
Requires-Dist: trame-vuetify
Requires-Dist: trame-components
Requires-Dist: vtk
Requires-Dist: numba
Requires-Dist: tqdm
Provides-Extra: gpu
Requires-Dist: cupy; extra == "gpu"
Provides-Extra: dev
Requires-Dist: pytest; extra == "dev"
Requires-Dist: pytest-mock; extra == "dev"
Requires-Dist: jupyter; extra == "dev"
Requires-Dist: jupyter-book; extra == "dev"
Dynamic: license-file
